particlewait.py
particle_wait-0.2.0.dist-info/DESCRIPTION.rst
particle_wait-0.2.0.dist-info/METADATA
particle_wait-0.2.0.dist-info/RECORD
particle_wait-0.2.0.dist-info/WHEEL
particle_wait-0.2.0.dist-info/entry_points.txt
particle_wait-0.2.0.dist-info/metadata.json
particle_wait-0.2.0.dist-info/top_level.txt
